RCPass/RCPass.py
RCPass/__init__.py
rcpass-0.0.1.dist-info/METADATA
rcpass-0.0.1.dist-info/WHEEL
rcpass-0.0.1.dist-info/licenses/LICENSE
rcpass-0.0.1.dist-info/RECORD
