Metadata-Version: 2.4
Name: RCPass
Version: 0.0.1
Summary: A package for password input masking
Project-URL: Homepage, https://github.com/sneekyfoxx/RCPass
Project-URL: Issues, https://github.com/sneekyfoxx/RCPass/issues
Author-email: sneekyfoxx <sneekyfoxx09@gmail.com>
License-Expression: MIT
License-File: LICENSE
Classifier: Operating System :: OS Independent
Classifier: Programming Language :: Python :: 3
Requires-Python: >=3.10
